tabulatepdf/__init__.py
tabulatepdf-0.1.1.data/scripts/tabulatepdf
tabulatepdf-0.1.1.dist-info/METADATA
tabulatepdf-0.1.1.dist-info/WHEEL
tabulatepdf-0.1.1.dist-info/top_level.txt
tabulatepdf-0.1.1.dist-info/RECORD
