Metadata-Version: 2.1
Name: tabulatepdf
Version: 0.1.1
Summary: A CLI for tabula-py
Home-page: https://github.com/Weizhang2017/tabulatepdf
Author: Wei Zhang
Author-email: zhangw1.2011@gmail.com
License: UNKNOWN
Platform: UNKNOWN
Classifier: Programming Language :: Python :: 3
Classifier: License :: OSI Approved :: MIT License
Classifier: Operating System :: OS Independent
Requires-Python: >=3.6
